qph/__init__.py
qph-1.0.0.dist-info/LICENSE.txt
qph-1.0.0.dist-info/METADATA
qph-1.0.0.dist-info/WHEEL
qph-1.0.0.dist-info/top_level.txt
qph-1.0.0.dist-info/RECORD
